chat/__init__.py
chat/api.py
chat/dependencies.py
chat/golden_gate_bridge.py
chat/modified_bundle.py
chat/server.py
chat/studio.py
chat/cli/__init__.py
chat/cli/agent_discovery.py
chat/cli/config_file.py
chat/cli/slug_generation.py
pydantic_work-0.1.11.dist-info/METADATA
pydantic_work-0.1.11.dist-info/WHEEL
pydantic_work-0.1.11.dist-info/entry_points.txt
pydantic_work-0.1.11.dist-info/top_level.txt
pydantic_work-0.1.11.dist-info/RECORD
