Metadata-Version: 2.4
Name: pydantic-work
Version: 0.1.11
Summary: A local-first chat UI for Pydantic AI agents
Author-email: David Sanchez <64162682+dsfaccini@users.noreply.github.com>
License-Expression: MIT
Project-URL: Homepage, https://github.com/dsfaccini/ai-chat-ui/tree/pydantic-work
Project-URL: Repository, https://github.com/dsfaccini/ai-chat-ui/tree/pydantic-work
Project-URL: Issues, https://github.com/dsfaccini/ai-chat-ui/tree/pydantic-work/issues
Project-URL: Twitter, https://x.com/dasfacc
Requires-Python: >=3.12
Requires-Dist: bs4>=0.0.2
Requires-Dist: fastapi>=0.117.1
Requires-Dist: httpx>=0.27.0
Requires-Dist: lancedb>=0.25.0
Requires-Dist: langchain-text-splitters>=0.3.11
Requires-Dist: logfire[fastapi]>=4.9.0
Requires-Dist: markdown2>=2.5.4
Requires-Dist: pip>=25.2
Requires-Dist: pydantic-ai-slim[anthropic,cli,google,openai]>=1.0.10
Requires-Dist: pyright>=1.1.405
Requires-Dist: python-frontmatter>=1.1.0
Requires-Dist: questionary>=2.0.0
Requires-Dist: sentence-transformers>=5.1.1
Requires-Dist: sse-starlette>=3.0.2
Requires-Dist: starlette>=0.48.0
Requires-Dist: uvicorn>=0.37.0
Requires-Dist: watchfiles>=1.1.0
